{
  "$schema": "http://json-schema.org/draft-07/schema#",
  "type": "object",
  "properties": {
    "source": {
      "type": "object",
      "properties": {
        "name": {
          "type": "string"
        },
        "slug": {
          "type": "string"
        },
        "logo": {
          "type": "string"
        }
      }
    },
    "calendar_date": {
      "type": "string"
    },
    "date": {
      "type": "string"
    },
    "id": {
      "type": "string"
    },
    "user_id": {
      "type": "string"
    },
    "user_key": {
      "type": ["null", "string"]
    },
    "calories_active": {
      "type": ["null", "number"]
    },
    "steps": {
      "type": ["null", "integer"]
    },
    "daily_movement": {
      "type": ["null", "number"]
    },
    "low": {
      "type": ["null", "number"]
    },
    "medium": {
      "type": ["null", "number"]
    },
    "high": {
      "type": ["null", "number"]
    },
    "floors_climbed": {
      "type": ["null", "integer"]
    },
    "time_zone": {
      "type": ["null", "string"]
    },
    "timezone_offset": {
      "type": ["null", "integer"]
    }
  }
}
